{
    "/js/user/app.js": "/js/user/app.js",
    "/js/user/auth.js": "/js/user/auth.js",
    "/js/lib/toasting.js": "/js/lib/toasting.js",
    "/js/admin/app.js": "/js/admin/app.js",
    "/js/admin/tag.js": "/js/admin/tag.js",
    "/css/user/app.css": "/css/user/app.css",
    "/css/admin/app.css": "/css/admin/app.css",
    "/css/user/auth.css": "/css/user/auth.css",
    "/css/lib/toasting.css": "/css/lib/toasting.css",
    "/css/admin/style.css": "/css/admin/style.css",
    "/js/magnific-popup.js": "/js/magnific-popup.js",
    "/js/jquery-slimscroll.js": "/js/jquery-slimscroll.js",
    "/js/bootstrap-datepicker.js": "/js/bootstrap-datepicker.js",
    "/js/lib/datatable.js": "/js/lib/datatable.js",
    "/css/lib/datatable.css": "/css/lib/datatable.css",
    "/js/lib/select2.js": "/js/lib/select2.js",
    "/css/lib/select2.css": "/css/lib/select2.css",
    "/js/lib/wow.js": "/js/lib/wow.js",
    "/css/img/footer_bg.jpg": "/css/img/footer_bg.jpg",
    "/css/bootstrap-datepicker.css": "/css/bootstrap-datepicker.css",
    "/css/admin/tag.css": "/css/admin/tag.css"
}
